pellets/__init__.py
pellets/config.py
pellets/pellet.py
pellets/records.py
pellets/utils/logger.py
pellets-0.1.1.dist-info/LICENSE.md
pellets-0.1.1.dist-info/METADATA
pellets-0.1.1.dist-info/WHEEL
pellets-0.1.1.dist-info/RECORD
